clirk/__init__.abi3.so
clirk/setting.abi3.so
clirk-1.4.5.dist-info/licenses/project/LICENSE
clirk-1.4.5.dist-info/METADATA
clirk-1.4.5.dist-info/WHEEL
clirk-1.4.5.dist-info/entry_points.txt
clirk-1.4.5.dist-info/top_level.txt
clirk-1.4.5.dist-info/RECORD
