Metadata-Version: 2.4
Name: clirk
Version: 1.4.5
Summary: project description
Author-email: YL <fengyulong@pku.org.cn>
License-Expression: MIT
Project-URL: homepage, https://gitee.com
Project-URL: documentation, https://gitee.com
Project-URL: bugs, https://gitee.com
Classifier: Development Status :: 5 - Production/Stable
Classifier: Intended Audience :: Developers
Classifier: Intended Audience :: Science/Research
Classifier: Natural Language :: Chinese (Simplified)
Classifier: Natural Language :: English
Classifier: Operating System :: Microsoft :: Windows
Classifier: Operating System :: POSIX :: Linux
Classifier: Operating System :: MacOS :: MacOS X
Classifier: Programming Language :: Python :: 3.12
Classifier: Topic :: Scientific/Engineering :: Physics
Requires-Python: >=3.12
License-File: project/LICENSE
Requires-Dist: pip
Requires-Dist: proxy.py
Requires-Dist: requests
Requires-Dist: srpc>=4.2.8
Provides-Extra: remote
Requires-Dist: inset; extra == "remote"
Requires-Dist: anyon; extra == "remote"
Provides-Extra: server
Requires-Dist: vios; extra == "server"
Requires-Dist: anyon; extra == "server"
Provides-Extra: studio
Requires-Dist: qwark; extra == "studio"
Provides-Extra: full
Requires-Dist: inset; extra == "full"
Requires-Dist: vios; extra == "full"
Requires-Dist: qwark; extra == "full"
Requires-Dist: anyon; extra == "full"
Dynamic: license-file
